image_converter/__init__.py
image_converter/__main__.py
image_converter/code_recognizer.py
code_image_to_text-0.1.4.dist-info/WHEEL
code_image_to_text-0.1.4.dist-info/METADATA
code_image_to_text-0.1.4.dist-info/RECORD
