Metadata-Version: 2.1
Name: code-image-to-text
Version: 0.1.4
Summary: Convert code image to text
Home-page: https://github.com/khuyentran1401/code_image_to_text
License: Apache-2.0
Keywords: computer vision,code
Author: khuyentran1401
Author-email: khuyentran1476@gmail.com
Requires-Python: >=3.7.1,<4.0.0
Classifier: License :: OSI Approved :: Apache Software License
Classifier: Programming Language :: Python :: 3
Classifier: Programming Language :: Python :: 3.8
Classifier: Programming Language :: Python :: 3.9
Requires-Dist: opencv-python (>=4.5.2,<5.0.0)
Requires-Dist: pytesseract (>=0.3.7,<0.4.0)
Requires-Dist: rich (>=10.2.2,<11.0.0)
Requires-Dist: typer (>=0.3.2,<0.4.0)
Project-URL: Repository, https://github.com/khuyentran1401/code_image_to_text
